odoo/addons/l10n_fi_banks/README.rst
odoo/addons/l10n_fi_banks/__init__.py
odoo/addons/l10n_fi_banks/__manifest__.py
odoo/addons/l10n_fi_banks/data/res_bank.xml
odoo/addons/l10n_fi_banks/i18n/fi.po
odoo/addons/l10n_fi_banks/i18n/l10n_fi_banks.pot
odoo/addons/l10n_fi_banks/readme/CONFIGURE.rst
odoo/addons/l10n_fi_banks/readme/CONTRIBUTORS.rst
odoo/addons/l10n_fi_banks/readme/CREDITS.rst
odoo/addons/l10n_fi_banks/readme/DESCRIPTION.rst
odoo/addons/l10n_fi_banks/readme/HISTORY.rst
odoo/addons/l10n_fi_banks/readme/MAINTAINER.rst
odoo/addons/l10n_fi_banks/static/description/icon.png
odoo/addons/l10n_fi_banks/static/description/index.html
odoo14_addon_l10n_fi_banks-14.0.1.0.1.dev4.dist-info/METADATA
odoo14_addon_l10n_fi_banks-14.0.1.0.1.dev4.dist-info/WHEEL
odoo14_addon_l10n_fi_banks-14.0.1.0.1.dev4.dist-info/top_level.txt
odoo14_addon_l10n_fi_banks-14.0.1.0.1.dev4.dist-info/RECORD
